greatapi/__init__.py
greatapi/config.py
greatapi/admin/__init__.py
greatapi/admin/sites.py
greatapi/admin/static/__init__.py
greatapi/admin/static/favicon.ico
greatapi/admin/static/greatapi_readme.svg
greatapi/admin/static/logo.svg
greatapi/admin/static/main.js
greatapi/admin/static/styles.css
greatapi/admin/templates/__init__.py
greatapi/admin/templates/base.html
greatapi/admin/templates/navbar.html
greatapi/admin/templates/sidebar.html
greatapi/admin/templates/authentication/__init__.py
greatapi/admin/templates/authentication/login.html
greatapi/admin/templates/dashboard/__init__.py
greatapi/admin/templates/dashboard/account.html
greatapi/admin/templates/dashboard/add_item.html
greatapi/admin/templates/dashboard/delete_user.html
greatapi/admin/templates/dashboard/group.html
greatapi/admin/templates/dashboard/history.html
greatapi/admin/templates/dashboard/index.html
greatapi/admin/templates/dashboard/items.html
greatapi/admin/templates/dashboard/settings.html
greatapi/admin/templates/dashboard/visualization.html
greatapi/commands/__init__.py
greatapi/commands/createsuperuser.py
greatapi/commands/runserver.py
greatapi/commands/startapp.py
greatapi/commands/startproject.py
greatapi/conf/__init__.py
greatapi/conf/app_template/__init__.py
greatapi/conf/app_template/__init__.py-tpl
greatapi/conf/app_template/models.py-tpl
greatapi/conf/app_template/repository.py-tpl
greatapi/conf/app_template/router.py-tpl
greatapi/conf/app_template/schemas.py-tpl
greatapi/conf/project_template/__init__.py
greatapi/conf/project_template/main.py-tpl
greatapi/conf/project_template/project_name/__init__.py
greatapi/conf/project_template/project_name/__init__.py-tpl
greatapi/conf/project_template/project_name/settings.py-tpl
greatapi/core/__init__.py
greatapi/core/auth/__init__.py
greatapi/core/auth/hashing.py
greatapi/core/auth/jwt_token.py
greatapi/core/auth/schemas.py
greatapi/core/auth/sites.py
greatapi/core/history/__init__.py
greatapi/core/history/repository.py
greatapi-1.0.0.dist-info/LICENSE
greatapi-1.0.0.dist-info/METADATA
greatapi-1.0.0.dist-info/WHEEL
greatapi-1.0.0.dist-info/entry_points.txt
greatapi-1.0.0.dist-info/top_level.txt
greatapi-1.0.0.dist-info/RECORD
