Metadata-Version: 2.1
Name: greatapi
Version: 1.0.0
Summary: GreatAPI framework, Full stack FastAPI framework.
Home-page: https://github.com/sahajrajmalla/greatapi
Author: Sahaj Raj Malla
Author-email: mallasahajraj@gmail.com
License: MIT
Platform: UNKNOWN
Classifier: Environment :: Web Environment
Classifier: Intended Audience :: Developers
Classifier: Intended Audience :: Information Technology
Classifier: Intended Audience :: System Administrators
Classifier: License :: OSI Approved :: MIT License
Classifier: Operating System :: OS Independent
Classifier: Programming Language :: Python
Classifier: Programming Language :: Python :: 3
Classifier: Programming Language :: Python :: 3 :: Only
Classifier: Programming Language :: Python :: 3.6
Classifier: Programming Language :: Python :: 3.7
Classifier: Programming Language :: Python :: 3.8
Classifier: Programming Language :: Python :: 3.9
Classifier: Programming Language :: Python :: 3.10
Classifier: Topic :: Internet
Classifier: Topic :: Internet :: WWW/HTTP
Classifier: Topic :: Internet :: WWW/HTTP :: HTTP Servers
Classifier: Topic :: Software Development
Classifier: Topic :: Software Development :: Libraries
Classifier: Topic :: Software Development :: Libraries :: Application Frameworks
Classifier: Topic :: Software Development :: Libraries :: Python Modules
Classifier: Typing :: Typed
Requires-Python: >=3.6.1
Requires-Dist: fastapi (<0.79.0,>=0.78.0)
Requires-Dist: jinja2 (<4.0.0,>=2.11.2)
Requires-Dist: passlib[bcrypt] (<2.0.0,>=1.7.2)
Requires-Dist: pre-commit (<3.0.0,>=2.17.0)
Requires-Dist: python-jose[cryptography] (<4.0.0,>=3.3.0)
Requires-Dist: python-multipart (<0.0.6,>=0.0.5)
Requires-Dist: sqlalchemy (<1.5.0,>=1.3.18)
Requires-Dist: typer (<0.5.0,>=0.4.1)
Requires-Dist: uvicorn[standard] (<0.18.0,>=0.12.0)
Provides-Extra: dev
Requires-Dist: pytest ; extra == 'dev'
